verify_code_identification/__init__.py
verify_code_identification/verify_code.py
verify_code_identifier-0.1.0.dist-info/METADATA
verify_code_identifier-0.1.0.dist-info/WHEEL
verify_code_identifier-0.1.0.dist-info/top_level.txt
verify_code_identifier-0.1.0.dist-info/RECORD
