Metadata-Version: 2.4
Name: verify-code-identifier
Version: 0.1.0
Summary: 基于ddddocr的验证码识别工具库
Author: kujq
Author-email: fmsws9@qq.com
Classifier: Development Status :: 4 - Beta
Classifier: Intended Audience :: Developers
Classifier: License :: OSI Approved :: MIT License
Classifier: Operating System :: OS Independent
Classifier: Programming Language :: Python :: 3
Classifier: Programming Language :: Python :: 3.6
Classifier: Programming Language :: Python :: 3.7
Classifier: Programming Language :: Python :: 3.8
Classifier: Programming Language :: Python :: 3.9
Requires-Python: >=3.6
Requires-Dist: ddddocr>=1.4.0
Requires-Dist: requests>=2.25.0
Requires-Dist: loguru>=0.5.0
Requires-Dist: Pillow>=8.0.0
Requires-Dist: onnxruntime>=1.8.0
Requires-Dist: numpy>=1.21.0
Dynamic: author
Dynamic: author-email
Dynamic: classifier
Dynamic: description
Dynamic: description-content-type
Dynamic: requires-dist
Dynamic: requires-python
Dynamic: summary
